sproject/__init__.py
sproject/file_organizer.py
sproject-0.0.6.dist-info/LICENSE.txt
sproject-0.0.6.dist-info/METADATA
sproject-0.0.6.dist-info/WHEEL
sproject-0.0.6.dist-info/top_level.txt
sproject-0.0.6.dist-info/RECORD
